LICENSE
MANIFEST.in
README.md
setup.py
flask_admin_markdown/__init__.py
flask_admin_markdown/view.py
flask_admin_markdown.egg-info/PKG-INFO
flask_admin_markdown.egg-info/SOURCES.txt
flask_admin_markdown.egg-info/dependency_links.txt
flask_admin_markdown.egg-info/requires.txt
flask_admin_markdown.egg-info/top_level.txt
flask_admin_markdown/ckeditor/__init__.py
flask_admin_markdown/ckeditor/fields.py
flask_admin_markdown/ckeditor/upload/__init__.py
flask_admin_markdown/ckeditor/upload/filename.py
flask_admin_markdown/ckeditor/upload/response.py
flask_admin_markdown/ckeditor/upload/uploader.py
flask_admin_markdown/markdown/__init__.py
flask_admin_markdown/static/editormd/.gitignore
flask_admin_markdown/static/editormd/.jshintrc
flask_admin_markdown/static/editormd/BUGS.md
flask_admin_markdown/static/editormd/CHANGE.md
flask_admin_markdown/static/editormd/Gulpfile.js
flask_admin_markdown/static/editormd/LICENSE
flask_admin_markdown/static/editormd/README.md
flask_admin_markdown/static/editormd/bower.json
flask_admin_markdown/static/editormd/editormd.amd.js
flask_admin_markdown/static/editormd/editormd.amd.min.js
flask_admin_markdown/static/editormd/editormd.js
flask_admin_markdown/static/editormd/editormd.min.js
flask_admin_markdown/static/editormd/package.json
flask_admin_markdown/static/editormd/css/editormd.css
flask_admin_markdown/static/editormd/css/editormd.logo.css
flask_admin_markdown/static/editormd/css/editormd.logo.min.css
flask_admin_markdown/static/editormd/css/editormd.min.css
flask_admin_markdown/static/editormd/css/editormd.preview.css
flask_admin_markdown/static/editormd/css/editormd.preview.min.css
flask_admin_markdown/static/editormd/docs/editormd.js.html
flask_admin_markdown/static/editormd/docs/index.html
flask_admin_markdown/static/editormd/docs/fonts/OpenSans-Bold-webfont.eot
flask_admin_markdown/static/editormd/docs/fonts/OpenSans-Bold-webfont.svg
flask_admin_markdown/static/editormd/docs/fonts/OpenSans-Bold-webfont.woff
flask_admin_markdown/static/editormd/docs/fonts/OpenSans-BoldItalic-webfont.eot
flask_admin_markdown/static/editormd/docs/fonts/OpenSans-BoldItalic-webfont.svg
flask_admin_markdown/static/editormd/docs/fonts/OpenSans-BoldItalic-webfont.woff
