Metadata-Version: 2.1
Name: flask-admin-markdown
Version: 2020.3.27.1
Summary: markdown for flask-admin
Home-page: https://github.com/suckmybigdick/flask-admin-markdown
Author-email: 13750192465@163.com
License: UNKNOWN
Platform: UNKNOWN
Classifier: Programming Language :: Python :: 3
Classifier: License :: OSI Approved :: MIT License
Classifier: Operating System :: OS Independent
